README.rst
setup.py
src/redis_json_storage/__init__.py
src/redis_json_storage/base.py
src/redis_json_storage/tests.py
src/reids_json_storage.egg-info/PKG-INFO
src/reids_json_storage.egg-info/SOURCES.txt
src/reids_json_storage.egg-info/dependency_links.txt
src/reids_json_storage.egg-info/not-zip-safe
src/reids_json_storage.egg-info/requires.txt
src/reids_json_storage.egg-info/top_level.txt