Metadata-Version: 1.1
Name: reids-json-storage
Version: 0.2.0
Summary: Redis json stroage.
Home-page: https://github.com/appstore-zencore/redis-json-storage
Author: zencore
Author-email: dobetter@zencore.cn
License: MIT
Keywords: reids-json-storage
Platform: UNKNOWN
Classifier: Development Status :: 5 - Production/Stable
Classifier: Intended Audience :: Developers
Classifier: Topic :: Software Development :: Libraries :: Python Modules
Classifier: License :: OSI Approved :: MIT License
Classifier: Programming Language :: Python :: 3
Classifier: Programming Language :: Python :: 3 :: Only
Requires: redis
